thesaurize_loader/__init__.py
thesaurize_loader/__main__.py
thesaurize_loader/loader.py
thesaurize_loader/protocols.py
thesaurize_loader-0.2.3.dist-info/entry_points.txt
thesaurize_loader-0.2.3.dist-info/WHEEL
thesaurize_loader-0.2.3.dist-info/METADATA
thesaurize_loader-0.2.3.dist-info/RECORD
