Metadata-Version: 2.1
Name: thesaurize-loader
Version: 0.2.3
Summary: Load OpenOffice thesaurus files into Redis
Home-page: https://github.com/MrFlynn/thesaurize/tree/master/tools/loader-tool
Author: Nick Pleatsikas
Author-email: nick@pleatsikas.me
Requires-Python: >=3.8,<4.0
Classifier: Programming Language :: Python :: 3
Classifier: Programming Language :: Python :: 3.8
Classifier: Topic :: Database
Classifier: Topic :: Utilities
Requires-Dist: aioredis (>=1.3.1,<2.0.0)
Requires-Dist: progress (>=1.5,<2.0)
Requires-Dist: requests (>=2.24.0,<3.0.0)
Project-URL: Repository, https://github.com/MrFlynn/thesaurize/
